odoo10_addon_geoengine_partner-10.0.1.0.1-nspkg.pth
odoo/addons/geoengine_partner/README.rst
odoo/addons/geoengine_partner/__init__.py
odoo/addons/geoengine_partner/__manifest__.py
odoo/addons/geoengine_partner/i18n/geoengine_partner.pot
odoo/addons/geoengine_partner/models/__init__.py
odoo/addons/geoengine_partner/models/partner.py
odoo/addons/geoengine_partner/static/description/icon.png
odoo/addons/geoengine_partner/views/partner.xml
odoo10_addon_geoengine_partner-10.0.1.0.1.dist-info/METADATA
odoo10_addon_geoengine_partner-10.0.1.0.1.dist-info/WHEEL
odoo10_addon_geoengine_partner-10.0.1.0.1.dist-info/namespace_packages.txt
odoo10_addon_geoengine_partner-10.0.1.0.1.dist-info/top_level.txt
odoo10_addon_geoengine_partner-10.0.1.0.1.dist-info/RECORD
